{
  "type": "GROUP",
"name": "Global Information",
"path": "",
"pathFormatted": "group_missing-name-b06d1",
"stats": {
    "name": "Global Information",
    "numberOfRequests": {
        "total": 104625,
        "ok": 98283,
        "ko": 6342
    },
    "minResponseTime": {
        "total": 0,
        "ok": 0,
        "ko": 2000
    },
    "maxResponseTime": {
        "total": 60021,
        "ok": 59953,
        "ko": 60021
    },
    "meanResponseTime": {
        "total": 6991,
        "ok": 6902,
        "ko": 8365
    },
    "standardDeviation": {
        "total": 13195,
        "ok": 13105,
        "ko": 14462
    },
    "percentiles1": {
        "total": 723,
        "ok": 277,
        "ko": 2037
    },
    "percentiles2": {
        "total": 4149,
        "ok": 4227,
        "ko": 2296
    },
    "percentiles3": {
        "total": 37238,
        "ok": 37292,
        "ko": 36612
    },
    "percentiles4": {
        "total": 51937,
        "ok": 51749,
        "ko": 60007
    },
    "group1": {
    "name": "t < 800 ms",
    "count": 53255,
    "percentage": 51
},
    "group2": {
    "name": "800 ms < t < 1200 ms",
    "count": 3036,
    "percentage": 3
},
    "group3": {
    "name": "t > 1200 ms",
    "count": 41992,
    "percentage": 40
},
    "group4": {
    "name": "failed",
    "count": 6342,
    "percentage": 6
},
    "meanNumberOfRequestsPerSecond": {
        "total": 255.1829268292683,
        "ok": 239.71463414634147,
        "ko": 15.46829268292683
    }
},
"contents": {
"req_home-8cf04": {
        "type": "REQUEST",
        "name": "Home",
"path": "Home",
"pathFormatted": "req_home-8cf04",
"stats": {
    "name": "Home",
    "numberOfRequests": {
        "total": 10000,
        "ok": 8192,
        "ko": 1808
    },
    "minResponseTime": {
        "total": 13,
        "ok": 13,
        "ko": 2088
    },
    "maxResponseTime": {
        "total": 60019,
        "ok": 11317,
        "ko": 60019
    },
    "meanResponseTime": {
        "total": 2974,
        "ok": 2427,
        "ko": 5448
    },
    "standardDeviation": {
        "total": 5943,
        "ok": 1731,
        "ko": 13201
    },
    "percentiles1": {
        "total": 2217,
        "ok": 1755,
        "ko": 2257
    },
    "percentiles2": {
        "total": 3888,
        "ok": 4087,
        "ko": 2315
    },
    "percentiles3": {
        "total": 5149,
        "ok": 5098,
        "ko": 60001
    },
    "percentiles4": {
        "total": 11804,
        "ok": 7087,
        "ko": 60008
    },
    "group1": {
    "name": "t < 800 ms",
    "count": 1518,
    "percentage": 15
},
    "group2": {
    "name": "800 ms < t < 1200 ms",
    "count": 767,
    "percentage": 8
},
    "group3": {
    "name": "t > 1200 ms",
    "count": 5907,
    "percentage": 59
},
    "group4": {
    "name": "failed",
    "count": 1808,
    "percentage": 18
},
    "meanNumberOfRequestsPerSecond": {
        "total": 24.390243902439025,
        "ok": 19.98048780487805,
        "ko": 4.409756097560976
    }
}
    },"req_login-99dea": {
        "type": "REQUEST",
        "name": "Login",
"path": "Login",
"pathFormatted": "req_login-99dea",
"stats": {
    "name": "Login",
    "numberOfRequests": {
        "total": 10000,
        "ok": 8192,
        "ko": 1808
    },
    "minResponseTime": {
        "total": 1,
        "ok": 1,
        "ko": 2000
    },
    "maxResponseTime": {
        "total": 4891,
        "ok": 4891,
        "ko": 2057
    },
    "meanResponseTime": {
        "total": 2054,
        "ok": 2061,
        "ko": 2020
    },
    "standardDeviation": {
        "total": 1667,
        "ok": 1842,
        "ko": 11
    },
    "percentiles1": {
        "total": 2021,
        "ok": 2398,
        "ko": 2018
    },
    "percentiles2": {
        "total": 3539,
        "ok": 3976,
        "ko": 2026
    },
    "percentiles3": {
        "total": 4594,
        "ok": 4604,
        "ko": 2041
    },
    "percentiles4": {
        "total": 4673,
        "ok": 4687,
        "ko": 2051
    },
    "group1": {
    "name": "t < 800 ms",
    "count": 3348,
    "percentage": 33
},
    "group2": {
    "name": "800 ms < t < 1200 ms",
    "count": 170,
    "percentage": 2
},
    "group3": {
    "name": "t > 1200 ms",
    "count": 4674,
    "percentage": 47
},
    "group4": {
    "name": "failed",
    "count": 1808,
    "percentage": 18
},
    "meanNumberOfRequestsPerSecond": {
        "total": 24.390243902439025,
        "ok": 19.98048780487805,
        "ko": 4.409756097560976
    }
}
    },"req_loggedcliente-c2a95": {
        "type": "REQUEST",
        "name": "LoggedCliente",
"path": "LoggedCliente",
"pathFormatted": "req_loggedcliente-c2a95",
"stats": {
    "name": "LoggedCliente",
    "numberOfRequests": {
        "total": 4096,
        "ok": 4096,
        "ko": 0
    },
    "minResponseTime": {
        "total": 1,
        "ok": 1,
        "ko": 0
    },
    "maxResponseTime": {
        "total": 7432,
        "ok": 7432,
        "ko": 0
    },
    "meanResponseTime": {
        "total": 1112,
        "ok": 1112,
        "ko": 0
    },
    "standardDeviation": {
        "total": 1080,
        "ok": 1080,
        "ko": 0
    },
    "percentiles1": {
        "total": 825,
        "ok": 824,
        "ko": 0
    },
    "percentiles2": {
        "total": 1890,
        "ok": 1890,
        "ko": 0
    },
    "percentiles3": {
        "total": 2890,
        "ok": 2890,
        "ko": 0
    },
    "percentiles4": {
        "total": 4236,
        "ok": 4236,
        "ko": 0
    },
    "group1": {
    "name": "t < 800 ms",
    "count": 2016,
    "percentage": 49
},
    "group2": {
    "name": "800 ms < t < 1200 ms",
    "count": 550,
    "percentage": 13
},
    "group3": {
    "name": "t > 1200 ms",
    "count": 1530,
    "percentage": 37
},
    "group4": {
    "name": "failed",
    "count": 0,
    "percentage": 0
},
    "meanNumberOfRequestsPerSecond": {
        "total": 9.990243902439024,
        "ok": 9.990243902439024,
        "ko": 0
    }
}
    },"req_loggedcliente-r-8e124": {
        "type": "REQUEST",
        "name": "LoggedCliente Redirect 1",
"path": "LoggedCliente Redirect 1",
"pathFormatted": "req_loggedcliente-r-8e124",
"stats": {
    "name": "LoggedCliente Redirect 1",
    "numberOfRequests": {
        "total": 4096,
        "ok": 4096,
        "ko": 0
    },
    "minResponseTime": {
        "total": 1,
        "ok": 1,
        "ko": 0
    },
    "maxResponseTime": {
        "total": 7775,
        "ok": 7775,
        "ko": 0
    },
    "meanResponseTime": {
        "total": 1368,
        "ok": 1368,
        "ko": 0
    },
    "standardDeviation": {
        "total": 1185,
        "ok": 1185,
        "ko": 0
    },
    "percentiles1": {
        "total": 1535,
        "ok": 1535,
        "ko": 0
    },
    "percentiles2": {
        "total": 2230,
        "ok": 2230,
        "ko": 0
    },
    "percentiles3": {
        "total": 3128,
        "ok": 3128,
        "ko": 0
    },
    "percentiles4": {
        "total": 4234,
        "ok": 4234,
        "ko": 0
    },
    "group1": {
    "name": "t < 800 ms",
    "count": 1596,
    "percentage": 39
},
    "group2": {
    "name": "800 ms < t < 1200 ms",
    "count": 66,
    "percentage": 2
},
    "group3": {
    "name": "t > 1200 ms",
    "count": 2434,
    "percentage": 59
},
    "group4": {
    "name": "failed",
    "count": 0,
    "percentage": 0
},
    "meanNumberOfRequestsPerSecond": {
        "total": 9.990243902439024,
        "ok": 9.990243902439024,
        "ko": 0
    }
}
    },"req_loggedadmin-c9137": {
        "type": "REQUEST",
        "name": "LoggedAdmin",
"path": "LoggedAdmin",
"pathFormatted": "req_loggedadmin-c9137",
"stats": {
    "name": "LoggedAdmin",
    "numberOfRequests": {
        "total": 4096,
        "ok": 4096,
        "ko": 0
    },
    "minResponseTime": {
        "total": 1,
        "ok": 1,
        "ko": 0
    },
    "maxResponseTime": {
        "total": 6517,
        "ok": 6517,
        "ko": 0
    },
    "meanResponseTime": {
        "total": 1098,
        "ok": 1098,
        "ko": 0
    },
    "standardDeviation": {
        "total": 1070,
        "ok": 1070,
        "ko": 0
    },
    "percentiles1": {
        "total": 815,
        "ok": 816,
        "ko": 0
    },
    "percentiles2": {
        "total": 1886,
        "ok": 1881,
        "ko": 0
    },
    "percentiles3": {
        "total": 2889,
        "ok": 2889,
        "ko": 0
    },
    "percentiles4": {
        "total": 3977,
        "ok": 3977,
        "ko": 0
    },
    "group1": {
    "name": "t < 800 ms",
    "count": 2030,
    "percentage": 50
},
    "group2": {
    "name": "800 ms < t < 1200 ms",
    "count": 533,
    "percentage": 13
},
    "group3": {
    "name": "t > 1200 ms",
    "count": 1533,
    "percentage": 37
},
    "group4": {
    "name": "failed",
    "count": 0,
    "percentage": 0
},
    "meanNumberOfRequestsPerSecond": {
        "total": 9.990243902439024,
        "ok": 9.990243902439024,
        "ko": 0
    }
}
    },"req_loggedadmin-red-4763c": {
        "type": "REQUEST",
        "name": "LoggedAdmin Redirect 1",
"path": "LoggedAdmin Redirect 1",
"pathFormatted": "req_loggedadmin-red-4763c",
"stats": {
    "name": "LoggedAdmin Redirect 1",
    "numberOfRequests": {
        "total": 4096,
        "ok": 4096,
        "ko": 0
    },
    "minResponseTime": {
        "total": 2,
        "ok": 2,
        "ko": 0
    },
    "maxResponseTime": {
        "total": 7545,
        "ok": 7545,
        "ko": 0
    },
    "meanResponseTime": {
        "total": 1373,
        "ok": 1373,
        "ko": 0
    },
    "standardDeviation": {
        "total": 1197,
        "ok": 1197,
        "ko": 0
    },
    "percentiles1": {
        "total": 1535,
        "ok": 1535,
        "ko": 0
    },
    "percentiles2": {
        "total": 2235,
        "ok": 2235,
        "ko": 0
    },
    "percentiles3": {
        "total": 3152,
        "ok": 3152,
        "ko": 0
    },
    "percentiles4": {
        "total": 4271,
        "ok": 4271,
        "ko": 0
    },
    "group1": {
    "name": "t < 800 ms",
    "count": 1605,
    "percentage": 39
},
    "group2": {
    "name": "800 ms < t < 1200 ms",
    "count": 54,
    "percentage": 1
},
    "group3": {
    "name": "t > 1200 ms",
    "count": 2437,
    "percentage": 59
},
    "group4": {
    "name": "failed",
    "count": 0,
    "percentage": 0
},
    "meanNumberOfRequestsPerSecond": {
        "total": 9.990243902439024,
        "ok": 9.990243902439024,
        "ko": 0
    }
}
    },"req_getlocales-83b8d": {
        "type": "REQUEST",
        "name": "GetLocales",
"path": "GetLocales",
"pathFormatted": "req_getlocales-83b8d",
"stats": {
    "name": "GetLocales",
    "numberOfRequests": {
        "total": 5000,
        "ok": 4146,
        "ko": 854
    },
    "minResponseTime": {
        "total": 1,
        "ok": 1,
        "ko": 2003
    },
    "maxResponseTime": {
        "total": 2054,
        "ok": 171,
        "ko": 2054
    },
    "meanResponseTime": {
        "total": 350,
        "ok": 7,
        "ko": 2019
    },
    "standardDeviation": {
        "total": 757,
        "ok": 12,
        "ko": 10
    },
    "percentiles1": {
        "total": 6,
        "ok": 5,
        "ko": 2017
    },
    "percentiles2": {
        "total": 9,
        "ok": 7,
        "ko": 2027
    },
    "percentiles3": {
        "total": 2021,
        "ok": 11,
        "ko": 2037
    },
    "percentiles4": {
        "total": 2036,
        "ok": 70,
        "ko": 2041
    },
    "group1": {
    "name": "t < 800 ms",
    "count": 4146,
    "percentage": 83
},
    "group2": {
    "name": "800 ms < t < 1200 ms",
    "count": 0,
    "percentage": 0
},
    "group3": {
    "name": "t > 1200 ms",
    "count": 0,
    "percentage": 0
},
    "group4": {
    "name": "failed",
    "count": 854,
    "percentage": 17
},
    "meanNumberOfRequestsPerSecond": {
        "total": 12.195121951219512,
        "ok": 10.112195121951219,
        "ko": 2.0829268292682928
    }
}
    },"req_detallelocal-1f5e5": {
        "type": "REQUEST",
        "name": "detalleLocal",
"path": "detalleLocal",
"pathFormatted": "req_detallelocal-1f5e5",
"stats": {
    "name": "detalleLocal",
    "numberOfRequests": {
        "total": 5000,
        "ok": 4146,
        "ko": 854
    },
    "minResponseTime": {
        "total": 2,
        "ok": 2,
        "ko": 2004
    },
    "maxResponseTime": {
        "total": 2069,
        "ok": 308,
        "ko": 2069
    },
    "meanResponseTime": {
        "total": 364,
        "ok": 21,
        "ko": 2026
    },
    "standardDeviation": {
        "total": 755,
        "ok": 33,
        "ko": 12
    },
    "percentiles1": {
        "total": 11,
        "ok": 9,
        "ko": 2026
    },
    "percentiles2": {
        "total": 60,
        "ok": 17,
        "ko": 2034
    },
    "percentiles3": {
        "total": 2030,
        "ok": 91,
        "ko": 2042
    },
    "percentiles4": {
        "total": 2042,
        "ok": 172,
        "ko": 2059
    },
    "group1": {
    "name": "t < 800 ms",
    "count": 4146,
    "percentage": 83
},
    "group2": {
    "name": "800 ms < t < 1200 ms",
    "count": 0,
    "percentage": 0
},
    "group3": {
    "name": "t > 1200 ms",
    "count": 0,
    "percentage": 0
},
    "group4": {
    "name": "failed",
    "count": 854,
    "percentage": 17
},
    "meanNumberOfRequestsPerSecond": {
        "total": 12.195121951219512,
        "ok": 10.112195121951219,
        "ko": 2.0829268292682928
    }
}
    },"req_aceptarlocal-31a33": {
        "type": "REQUEST",
        "name": "AceptarLocal",
"path": "AceptarLocal",
"pathFormatted": "req_aceptarlocal-31a33",
"stats": {
    "name": "AceptarLocal",
    "numberOfRequests": {
        "total": 5000,
        "ok": 5000,
        "ko": 0
    },
    "minResponseTime": {
        "total": 0,
        "ok": 0,
        "ko": 0
    },
    "maxResponseTime": {
        "total": 202,
        "ok": 202,
        "ko": 0
    },
    "meanResponseTime": {
        "total": 9,
        "ok": 9,
        "ko": 0
    },
    "standardDeviation": {
        "total": 10,
        "ok": 10,
        "ko": 0
    },
    "percentiles1": {
        "total": 6,
        "ok": 6,
        "ko": 0
    },
    "percentiles2": {
        "total": 9,
        "ok": 9,
        "ko": 0
    },
    "percentiles3": {
        "total": 20,
        "ok": 20,
        "ko": 0
    },
    "percentiles4": {
        "total": 54,
        "ok": 54,
        "ko": 0
    },
    "group1": {
    "name": "t < 800 ms",
    "count": 5000,
    "percentage": 100
},
    "group2": {
    "name": "800 ms < t < 1200 ms",
    "count": 0,
    "percentage": 0
},
    "group3": {
    "name": "t > 1200 ms",
    "count": 0,
    "percentage": 0
},
    "group4": {
    "name": "failed",
    "count": 0,
    "percentage": 0
},
    "meanNumberOfRequestsPerSecond": {
        "total": 12.195121951219512,
        "ok": 12.195121951219512,
        "ko": 0
    }
}
    },"req_aceptarlocal-re-c54bc": {
        "type": "REQUEST",
        "name": "AceptarLocal Redirect 1",
"path": "AceptarLocal Redirect 1",
"pathFormatted": "req_aceptarlocal-re-c54bc",
"stats": {
    "name": "AceptarLocal Redirect 1",
    "numberOfRequests": {
        "total": 5000,
        "ok": 5000,
        "ko": 0
    },
    "minResponseTime": {
        "total": 0,
        "ok": 0,
        "ko": 0
    },
    "maxResponseTime": {
        "total": 146,
        "ok": 146,
        "ko": 0
    },
    "meanResponseTime": {
        "total": 7,
        "ok": 7,
        "ko": 0
    },
    "standardDeviation": {
        "total": 8,
        "ok": 8,
        "ko": 0
    },
    "percentiles1": {
        "total": 5,
        "ok": 5,
        "ko": 0
    },
    "percentiles2": {
        "total": 8,
        "ok": 8,
        "ko": 0
    },
    "percentiles3": {
        "total": 17,
        "ok": 18,
        "ko": 0
    },
    "percentiles4": {
        "total": 41,
        "ok": 41,
        "ko": 0
    },
    "group1": {
    "name": "t < 800 ms",
    "count": 5000,
    "percentage": 100
},
    "group2": {
    "name": "800 ms < t < 1200 ms",
    "count": 0,
    "percentage": 0
},
    "group3": {
    "name": "t > 1200 ms",
    "count": 0,
    "percentage": 0
},
    "group4": {
    "name": "failed",
    "count": 0,
    "percentage": 0
},
    "meanNumberOfRequestsPerSecond": {
        "total": 12.195121951219512,
        "ok": 12.195121951219512,
        "ko": 0
    }
}
    },"req_logout-0323d": {
        "type": "REQUEST",
        "name": "Logout",
"path": "Logout",
"pathFormatted": "req_logout-0323d",
"stats": {
    "name": "Logout",
    "numberOfRequests": {
        "total": 10000,
        "ok": 10000,
        "ko": 0
    },
    "minResponseTime": {
        "total": 0,
        "ok": 0,
        "ko": 0
    },
    "maxResponseTime": {
        "total": 52238,
        "ok": 52238,
        "ko": 0
    },
    "meanResponseTime": {
        "total": 14093,
        "ok": 14093,
        "ko": 0
    },
    "standardDeviation": {
        "total": 19034,
        "ok": 19034,
        "ko": 0
    },
    "percentiles1": {
        "total": 7,
        "ok": 7,
        "ko": 0
    },
    "percentiles2": {
        "total": 29750,
        "ok": 29750,
        "ko": 0
    },
    "percentiles3": {
        "total": 51031,
        "ok": 51031,
        "ko": 0
    },
    "percentiles4": {
        "total": 52043,
        "ok": 52043,
        "ko": 0
    },
    "group1": {
    "name": "t < 800 ms",
    "count": 5694,
    "percentage": 57
},
    "group2": {
    "name": "800 ms < t < 1200 ms",
    "count": 48,
    "percentage": 0
},
    "group3": {
    "name": "t > 1200 ms",
    "count": 4258,
    "percentage": 43
},
    "group4": {
    "name": "failed",
    "count": 0,
    "percentage": 0
},
    "meanNumberOfRequestsPerSecond": {
        "total": 24.390243902439025,
        "ok": 24.390243902439025,
        "ko": 0
    }
}
    },"req_cofirmlogout-34f98": {
        "type": "REQUEST",
        "name": "CofirmLogout",
"path": "CofirmLogout",
"pathFormatted": "req_cofirmlogout-34f98",
"stats": {
    "name": "CofirmLogout",
    "numberOfRequests": {
        "total": 10000,
        "ok": 10000,
        "ko": 0
    },
    "minResponseTime": {
        "total": 0,
        "ok": 0,
        "ko": 0
    },
    "maxResponseTime": {
        "total": 52227,
        "ok": 52227,
        "ko": 0
    },
    "meanResponseTime": {
        "total": 4427,
        "ok": 4427,
        "ko": 0
    },
    "standardDeviation": {
        "total": 11904,
        "ok": 11904,
        "ko": 0
    },
    "percentiles1": {
        "total": 3,
        "ok": 3,
        "ko": 0
    },
    "percentiles2": {
        "total": 429,
        "ok": 429,
        "ko": 0
    },
    "percentiles3": {
        "total": 38345,
        "ok": 38345,
        "ko": 0
    },
    "percentiles4": {
        "total": 51010,
        "ok": 51010,
        "ko": 0
    },
    "group1": {
    "name": "t < 800 ms",
    "count": 7642,
    "percentage": 76
},
    "group2": {
    "name": "800 ms < t < 1200 ms",
    "count": 205,
    "percentage": 2
},
    "group3": {
    "name": "t > 1200 ms",
    "count": 2153,
    "percentage": 22
},
    "group4": {
    "name": "failed",
    "count": 0,
    "percentage": 0
},
    "meanNumberOfRequestsPerSecond": {
        "total": 24.390243902439025,
        "ok": 24.390243902439025,
        "ko": 0
    }
}
    },"req_cofirmlogout-re-7caaa": {
        "type": "REQUEST",
        "name": "CofirmLogout Redirect 1",
"path": "CofirmLogout Redirect 1",
"pathFormatted": "req_cofirmlogout-re-7caaa",
"stats": {
    "name": "CofirmLogout Redirect 1",
    "numberOfRequests": {
        "total": 10000,
        "ok": 10000,
        "ko": 0
    },
    "minResponseTime": {
        "total": 1,
        "ok": 1,
        "ko": 0
    },
    "maxResponseTime": {
        "total": 28817,
        "ok": 28817,
        "ko": 0
    },
    "meanResponseTime": {
        "total": 961,
        "ok": 961,
        "ko": 0
    },
    "standardDeviation": {
        "total": 2410,
        "ok": 2410,
        "ko": 0
    },
    "percentiles1": {
        "total": 7,
        "ok": 7,
        "ko": 0
    },
    "percentiles2": {
        "total": 262,
        "ok": 262,
        "ko": 0
    },
    "percentiles3": {
        "total": 6314,
        "ok": 6314,
        "ko": 0
    },
    "percentiles4": {
        "total": 11237,
        "ok": 11237,
        "ko": 0
    },
    "group1": {
    "name": "t < 800 ms",
    "count": 7855,
    "percentage": 79
},
    "group2": {
    "name": "800 ms < t < 1200 ms",
    "count": 517,
    "percentage": 5
},
    "group3": {
    "name": "t > 1200 ms",
    "count": 1628,
    "percentage": 16
},
    "group4": {
    "name": "failed",
    "count": 0,
    "percentage": 0
},
    "meanNumberOfRequestsPerSecond": {
        "total": 24.390243902439025,
        "ok": 24.390243902439025,
        "ko": 0
    }
}
    },"req_getlocales-redi-83539": {
        "type": "REQUEST",
        "name": "GetLocales Redirect 1",
"path": "GetLocales Redirect 1",
"pathFormatted": "req_getlocales-redi-83539",
"stats": {
    "name": "GetLocales Redirect 1",
    "numberOfRequests": {
        "total": 50,
        "ok": 50,
        "ko": 0
    },
    "minResponseTime": {
        "total": 0,
        "ok": 0,
        "ko": 0
    },
    "maxResponseTime": {
        "total": 5,
        "ok": 5,
        "ko": 0
    },
    "meanResponseTime": {
        "total": 2,
        "ok": 2,
        "ko": 0
    },
    "standardDeviation": {
        "total": 1,
        "ok": 1,
        "ko": 0
    },
    "percentiles1": {
        "total": 3,
        "ok": 3,
        "ko": 0
    },
    "percentiles2": {
        "total": 3,
        "ok": 3,
        "ko": 0
    },
    "percentiles3": {
        "total": 4,
        "ok": 4,
        "ko": 0
    },
    "percentiles4": {
        "total": 5,
        "ok": 5,
        "ko": 0
    },
    "group1": {
    "name": "t < 800 ms",
    "count": 50,
    "percentage": 100
},
    "group2": {
    "name": "800 ms < t < 1200 ms",
    "count": 0,
    "percentage": 0
},
    "group3": {
    "name": "t > 1200 ms",
    "count": 0,
    "percentage": 0
},
    "group4": {
    "name": "failed",
    "count": 0,
    "percentage": 0
},
    "meanNumberOfRequestsPerSecond": {
        "total": 0.12195121951219512,
        "ok": 0.12195121951219512,
        "ko": 0
    }
}
    },"req_misasistencias-3423d": {
        "type": "REQUEST",
        "name": "misAsistencias",
"path": "misAsistencias",
"pathFormatted": "req_misasistencias-3423d",
"stats": {
    "name": "misAsistencias",
    "numberOfRequests": {
        "total": 5000,
        "ok": 5000,
        "ko": 0
    },
    "minResponseTime": {
        "total": 11,
        "ok": 11,
        "ko": 0
    },
    "maxResponseTime": {
        "total": 49451,
        "ok": 49451,
        "ko": 0
    },
    "meanResponseTime": {
        "total": 8956,
        "ok": 8956,
        "ko": 0
    },
    "standardDeviation": {
        "total": 9030,
        "ok": 9030,
        "ko": 0
    },
    "percentiles1": {
        "total": 6083,
        "ok": 6090,
        "ko": 0
    },
    "percentiles2": {
        "total": 15548,
        "ok": 15537,
        "ko": 0
    },
    "percentiles3": {
        "total": 25689,
        "ok": 25689,
        "ko": 0
    },
    "percentiles4": {
        "total": 30841,
        "ok": 30841,
        "ko": 0
    },
    "group1": {
    "name": "t < 800 ms",
    "count": 1503,
    "percentage": 30
},
    "group2": {
    "name": "800 ms < t < 1200 ms",
    "count": 106,
    "percentage": 2
},
    "group3": {
    "name": "t > 1200 ms",
    "count": 3391,
    "percentage": 68
},
    "group4": {
    "name": "failed",
    "count": 0,
    "percentage": 0
},
    "meanNumberOfRequestsPerSecond": {
        "total": 12.195121951219512,
        "ok": 12.195121951219512,
        "ko": 0
    }
}
    },"req_verfiesta-0bd90": {
        "type": "REQUEST",
        "name": "verFiesta",
"path": "verFiesta",
"pathFormatted": "req_verfiesta-0bd90",
"stats": {
    "name": "verFiesta",
    "numberOfRequests": {
        "total": 5000,
        "ok": 4096,
        "ko": 904
    },
    "minResponseTime": {
        "total": 758,
        "ok": 758,
        "ko": 29097
    },
    "maxResponseTime": {
        "total": 60011,
        "ok": 55665,
        "ko": 60011
    },
    "meanResponseTime": {
        "total": 27763,
        "ok": 26749,
        "ko": 32357
    },
    "standardDeviation": {
        "total": 8233,
        "ok": 8349,
        "ko": 5771
    },
    "percentiles1": {
        "total": 29621,
        "ok": 29273,
        "ko": 30018
    },
    "percentiles2": {
        "total": 31156,
        "ok": 31015,
        "ko": 32217
    },
    "percentiles3": {
        "total": 36941,
        "ok": 35852,
        "ko": 47472
    },
    "percentiles4": {
        "total": 47670,
        "ok": 41378,
        "ko": 55887
    },
    "group1": {
    "name": "t < 800 ms",
    "count": 2,
    "percentage": 0
},
    "group2": {
    "name": "800 ms < t < 1200 ms",
    "count": 14,
    "percentage": 0
},
    "group3": {
    "name": "t > 1200 ms",
    "count": 4080,
    "percentage": 82
},
    "group4": {
    "name": "failed",
    "count": 904,
    "percentage": 18
},
    "meanNumberOfRequestsPerSecond": {
        "total": 12.195121951219512,
        "ok": 9.990243902439024,
        "ko": 2.204878048780488
    }
}
    },"req_valorar-40fa7": {
        "type": "REQUEST",
        "name": "Valorar",
"path": "Valorar",
"pathFormatted": "req_valorar-40fa7",
"stats": {
    "name": "Valorar",
    "numberOfRequests": {
        "total": 4096,
        "ok": 4095,
        "ko": 1
    },
    "minResponseTime": {
        "total": 23404,
        "ok": 23404,
        "ko": 60001
    },
    "maxResponseTime": {
        "total": 60001,
        "ok": 57264,
        "ko": 60001
    },
    "meanResponseTime": {
        "total": 30659,
        "ok": 30652,
        "ko": 60001
    },
    "standardDeviation": {
        "total": 4719,
        "ok": 4698,
        "ko": 0
    },
    "percentiles1": {
        "total": 30388,
        "ok": 30387,
        "ko": 60001
    },
    "percentiles2": {
        "total": 32042,
        "ok": 32038,
        "ko": 60001
    },
    "percentiles3": {
        "total": 39586,
        "ok": 39483,
        "ko": 60001
    },
    "percentiles4": {
        "total": 48349,
        "ok": 48300,
        "ko": 60001
    },
    "group1": {
    "name": "t < 800 ms",
    "count": 0,
    "percentage": 0
},
    "group2": {
    "name": "800 ms < t < 1200 ms",
    "count": 0,
    "percentage": 0
},
    "group3": {
    "name": "t > 1200 ms",
    "count": 4095,
    "percentage": 100
},
    "group4": {
    "name": "failed",
    "count": 1,
    "percentage": 0
},
    "meanNumberOfRequestsPerSecond": {
        "total": 9.990243902439024,
        "ok": 9.987804878048781,
        "ko": 0.0024390243902439024
    }
}
    },"req_valorar-redirec-7a896": {
        "type": "REQUEST",
        "name": "Valorar Redirect 1",
"path": "Valorar Redirect 1",
"pathFormatted": "req_valorar-redirec-7a896",
"stats": {
    "name": "Valorar Redirect 1",
    "numberOfRequests": {
        "total": 4095,
        "ok": 3982,
        "ko": 113
    },
    "minResponseTime": {
        "total": 41,
        "ok": 41,
        "ko": 60000
    },
    "maxResponseTime": {
        "total": 60021,
        "ok": 59953,
        "ko": 60021
    },
    "meanResponseTime": {
        "total": 37413,
        "ok": 36772,
        "ko": 60004
    },
    "standardDeviation": {
        "total": 13983,
        "ok": 13645,
        "ko": 5
    },
    "percentiles1": {
        "total": 36801,
        "ok": 35437,
        "ko": 60001
    },
    "percentiles2": {
        "total": 49345,
        "ok": 48492,
        "ko": 60002
    },
    "percentiles3": {
        "total": 57338,
        "ok": 56778,
        "ko": 60016
    },
    "percentiles4": {
        "total": 60002,
        "ok": 58128,
        "ko": 60020
    },
    "group1": {
    "name": "t < 800 ms",
    "count": 104,
    "percentage": 3
},
    "group2": {
    "name": "800 ms < t < 1200 ms",
    "count": 6,
    "percentage": 0
},
    "group3": {
    "name": "t > 1200 ms",
    "count": 3872,
    "percentage": 95
},
    "group4": {
    "name": "failed",
    "count": 113,
    "percentage": 3
},
    "meanNumberOfRequestsPerSecond": {
        "total": 9.987804878048781,
        "ok": 9.71219512195122,
        "ko": 0.275609756097561
    }
}
    }
}

}